adafruit_circuitpython_pybadger-4.0.7.dist-info/licenses/LICENSE
adafruit_pybadger/__init__.py
adafruit_pybadger/clue.py
adafruit_pybadger/cpb_gizmo.py
adafruit_pybadger/magtag.py
adafruit_pybadger/pewpewm4.py
adafruit_pybadger/pybadge.py
adafruit_pybadger/pybadger_base.py
adafruit_pybadger/pygamer.py
adafruit_pybadger/pyportal.py
adafruit_circuitpython_pybadger-4.0.7.dist-info/METADATA
adafruit_circuitpython_pybadger-4.0.7.dist-info/WHEEL
adafruit_circuitpython_pybadger-4.0.7.dist-info/top_level.txt
adafruit_circuitpython_pybadger-4.0.7.dist-info/RECORD
