Metadata-Version: 2.4
Name: adafruit-circuitpython-pybadger
Version: 4.0.7
Summary: Badge-focused CircuitPython helper library for PyBadge, PyBadge LC, PyGamer and CLUE
Author-email: Adafruit Industries <circuitpython@adafruit.com>
License: MIT
Project-URL: Homepage, https://github.com/adafruit/Adafruit_CircuitPython_PyBadger
Keywords: adafruit,pybadge,pygamer,clue,display,hardware,micropythoncircuitpython
Classifier: Intended Audience :: Developers
Classifier: Topic :: Software Development :: Libraries
Classifier: Topic :: Software Development :: Embedded Systems
Classifier: Topic :: System :: Hardware
Classifier: License :: OSI Approved :: MIT License
Classifier: Programming Language :: Python :: 3
License-File: LICENSE
Requires-Dist: Adafruit-Blinka
Requires-Dist: adafruit-circuitpython-bitmap-font
Requires-Dist: adafruit-circuitpython-lsm6ds
Requires-Dist: adafruit-circuitpython-display-text
Requires-Dist: adafruit-circuitpython-miniqr
Requires-Dist: adafruit-circuitpython-neopixel
Requires-Dist: adafruit-circuitpython-gizmo
Requires-Dist: adafruit-circuitpython-lis3dh
Requires-Dist: adafruit-circuitpython-display-shapes
Provides-Extra: optional
Dynamic: license-file
